{
    "personnages": [
        {"nom":"Sorcière","image":"https://raw.githubusercontent.com/eric-gilles/Projet_Prog/main/images/jsonlg/sorciere.png","attributs":{"ce personnage est un":["villageois"],"ce personnage est":["humain"],"son rôle peut":["tuer n'importe qui","sauver"],"ce personnage peut se réveiller":["toutes les nuits"]}},
        {"nom":"Petite Fille","image":"https://raw.githubusercontent.com/eric-gilles/Projet_Prog/main/images/jsonlg/pf.png","attributs":{"ce personnage est un":["villageois"],"ce personnage est":["humain"],"son rôle peut":["obtenir des informations"],"ce personnage peut se réveiller":["la nuit"]}},
        {"nom":"Infect Père des Loups","image":"https://raw.githubusercontent.com/eric-gilles/Projet_Prog/main/images/jsonlg/ipdl.png","attributs":{"ce personnage est un":["loup-garou"],"ce personnage est":["non humain"],"son rôle peut":["tuer que des villageois","sauver"],"ce personnage peut se réveiller":["toutes les nuits"]}},
        {"nom":"Loup Garou Blanc","image":"https://raw.githubusercontent.com/eric-gilles/Projet_Prog/main/images/jsonlg/lgb.jpg","attributs":{"ce personnage est un":["solitaire","loup-garou"],"ce personnage est":["non humain"],"son rôle peut":["tuer que des villageois","tuer que des loups-garous"],"ce personnage peut se réveiller":["toutes les nuits","une nuit sur deux"]}},
        {"nom":"Voyante","image":"https://raw.githubusercontent.com/eric-gilles/Projet_Prog/main/images/jsonlg/voyante.png","attributs":{"ce personnage est un":["villageois"],"ce personnage est":["humain"],"son rôle peut":["obtenir des informations"],"ce personnage peut se réveiller":["toutes les nuits"]}},
        {"nom":"Chasseur","image":"https://raw.githubusercontent.com/eric-gilles/Projet_Prog/main/images/jsonlg/chasseur.png","attributs":{"ce personnage est un":["villageois"],"ce personnage est":["humain"],"son rôle peut":["tuer n'importe qui"],"ce personnage peut se réveiller":[]}},
        {"nom":"Corbeau","image":"https://raw.githubusercontent.com/eric-gilles/Projet_Prog/main/images/jsonlg/corbeau.png","attributs":{"ce personnage est un":["villageois"],"ce personnage est":["non humain"],"son rôle peut":["influencer les votes"],"ce personnage peut se réveiller":["toutes les nuits"]}},
        {"nom":"Joueur de Flûte","image":"https://raw.githubusercontent.com/eric-gilles/Projet_Prog/main/images/jsonlg/jdf.jpg","attributs":{"ce personnage est un":["solitaire"],"ce personnage est":["humain"],"son rôle peut":["influencer les votes"],"ce personnage peut se réveiller":["toutes les nuits"]}},
        {"nom":"Assassin","image":"https://raw.githubusercontent.com/eric-gilles/Projet_Prog/main/images/jsonlg/assassin.png","attributs":{"ce personnage est un":["solitaire"],"ce personnage est":["humain"],"son rôle peut":["tuer n'importe qui"],"ce personnage peut se réveiller":["une nuit sur deux"]}},
        {"nom":"Montreur d'Ours","image":"https://raw.githubusercontent.com/eric-gilles/Projet_Prog/main/images/jsonlg/montreur.png","attributs":{"ce personnage est un":["villageois"],"ce personnage est":["humain"],"son rôle peut":["obtenir des informations"],"ce personnage peut se réveiller":[]}},
        {"nom":"Chevalier à l'Epée Rouillée","image":"https://raw.githubusercontent.com/eric-gilles/Projet_Prog/main/images/jsonlg/chevalier.png","attributs":{"ce personnage est un":["villageois"],"ce personnage est":["humain"],"son rôle peut":["tuer que des loups-garous"],"ce personnage peut se réveiller":[]}},
        {"nom":"Renard","image":"https://raw.githubusercontent.com/eric-gilles/Projet_Prog/main/images/jsonlg/renard.png","attributs":{"ce personnage est un":["villageois"],"ce personnage est":["non humain"],"son rôle peut":["obtenir des informations"],"ce personnage peut se réveiller":["toutes les nuits"]}},
        {"nom":"Salvateur","image":"https://raw.githubusercontent.com/eric-gilles/Projet_Prog/main/images/jsonlg/salvateur.png","attributs":{"ce personnage est un":["villageois"],"ce personnage est":["humain"],"son rôle peut":["sauver","survivre à une attaque des loups"],"ce personnage peut se réveiller":["toutes les nuits"]}},
        {"nom":"Loup Garou Simple","image":"https://raw.githubusercontent.com/eric-gilles/Projet_Prog/main/images/jsonlg/lg.png","attributs":{"ce personnage est un":["loup-garou"],"ce personnage est":["non humain"],"son rôle peut":["tuer que des villageois"],"ce personnage peut se réveiller":["toutes les nuits"]}},
        {"nom":"Ancien","image":"https://raw.githubusercontent.com/eric-gilles/Projet_Prog/main/images/jsonlg/ancien.png","attributs":{"ce personnage est un":["villageois"],"ce personnage est":["humain"],"son rôle peut":["survivre à une attaque des loups"],"ce personnage peut se réveiller":[]}}
    ]
}
